Metadata-Version: 2.1
Name: avi-mmdet
Version: 3.3.2
Summary: Custom OpenMMLab Detection Toolbox and Benchmark
Home-page: https://github.com/open-mmlab/mmdetection
Author: MMDetection Contributors
Author-email: openmmlab@gmail.com
License: Apache License 2.0
Keywords: computer vision,object detection
Platform: UNKNOWN
Classifier: Development Status :: 5 - Production/Stable
Classifier: License :: OSI Approved :: Apache Software License
Classifier: Operating System :: OS Independent
Classifier: Programming Language :: Python :: 3
Classifier: Programming Language :: Python :: 3.7
Classifier: Programming Language :: Python :: 3.8
Classifier: Programming Language :: Python :: 3.9
License-File: LICENSE
Requires-Dist: matplotlib
Requires-Dist: numpy
Requires-Dist: pycocotools
Requires-Dist: scipy
Requires-Dist: shapely
Requires-Dist: six
Requires-Dist: terminaltables
Requires-Dist: tqdm
Provides-Extra: all
Requires-Dist: cython; extra == "all"
Requires-Dist: numpy; extra == "all"
Requires-Dist: cityscapesscripts; extra == "all"
Requires-Dist: emoji; extra == "all"
Requires-Dist: fairscale; extra == "all"
Requires-Dist: imagecorruptions; extra == "all"
Requires-Dist: scikit-learn; extra == "all"
Requires-Dist: matplotlib; extra == "all"
Requires-Dist: pycocotools; extra == "all"
Requires-Dist: scipy; extra == "all"
Requires-Dist: shapely; extra == "all"
Requires-Dist: six; extra == "all"
Requires-Dist: terminaltables; extra == "all"
Requires-Dist: tqdm; extra == "all"
Provides-Extra: build
Requires-Dist: cython; extra == "build"
Requires-Dist: numpy; extra == "build"
Provides-Extra: mim
Requires-Dist: mmcv<2.2.0,>=2.0.0rc4; extra == "mim"
Requires-Dist: mmengine<1.0.0,>=0.7.1; extra == "mim"
Provides-Extra: multimodal
Requires-Dist: fairscale; extra == "multimodal"
Requires-Dist: jsonlines; extra == "multimodal"
Requires-Dist: nltk; extra == "multimodal"
Requires-Dist: pycocoevalcap; extra == "multimodal"
Requires-Dist: transformers; extra == "multimodal"
Provides-Extra: optional
Requires-Dist: cityscapesscripts; extra == "optional"
Requires-Dist: emoji; extra == "optional"
Requires-Dist: fairscale; extra == "optional"
Requires-Dist: imagecorruptions; extra == "optional"
Requires-Dist: scikit-learn; extra == "optional"
Provides-Extra: tests
Requires-Dist: asynctest; extra == "tests"
Requires-Dist: cityscapesscripts; extra == "tests"
Requires-Dist: codecov; extra == "tests"
Requires-Dist: flake8; extra == "tests"
Requires-Dist: imagecorruptions; extra == "tests"
Requires-Dist: instaboostfast; extra == "tests"
Requires-Dist: interrogate; extra == "tests"
Requires-Dist: isort==4.3.21; extra == "tests"
Requires-Dist: kwarray; extra == "tests"
Requires-Dist: memory-profiler; extra == "tests"
Requires-Dist: mmtrack; extra == "tests"
Requires-Dist: nltk; extra == "tests"
Requires-Dist: onnx==1.7.0; extra == "tests"
Requires-Dist: onnxruntime>=1.8.0; extra == "tests"
Requires-Dist: parameterized; extra == "tests"
Requires-Dist: prettytable; extra == "tests"
Requires-Dist: protobuf<=3.20.1; extra == "tests"
Requires-Dist: psutil; extra == "tests"
Requires-Dist: pytest; extra == "tests"
Requires-Dist: transformers; extra == "tests"
Requires-Dist: ubelt; extra == "tests"
Requires-Dist: xdoctest>=0.10.0; extra == "tests"
Requires-Dist: yapf; extra == "tests"
Provides-Extra: tracking
Requires-Dist: mmpretrain; extra == "tracking"
Requires-Dist: motmetrics; extra == "tracking"
Requires-Dist: numpy<1.24.0; extra == "tracking"
Requires-Dist: scikit-learn; extra == "tracking"
Requires-Dist: seaborn; extra == "tracking"
